neutralise_link/__init__.py
neutralise_link/logger.py
neutralise_link/main.py
neutralise_link/options.py
neutralise_link/utils.py
neutralise_link-0.1.3.dist-info/METADATA
neutralise_link-0.1.3.dist-info/WHEEL
neutralise_link-0.1.3.dist-info/licenses/LICENSE
neutralise_link-0.1.3.dist-info/RECORD
