Metadata-Version: 2.4
Name: neutralise_link
Version: 0.1.3
Summary: Validating, cleaning, and compactifying URLs simplified.
Project-URL: Homepage, https://github.com/brainpolo/neutralise-link
Project-URL: Bug Tracker, https://github.com/brainpolo/neutralise-link/issues
Author-email: Aditya Dedhia <aditya@brainpolo.com>
License-File: LICENSE
Classifier: License :: OSI Approved :: GNU General Public License v3 (GPLv3)
Classifier: Operating System :: OS Independent
Classifier: Programming Language :: Python :: 3
Classifier: Programming Language :: Python :: 3.10
Requires-Python: >=3.10
